README.md
pyproject.toml
time_measure_decorator/__init__.py
time_measure_decorator/common.py
time_measure_decorator/py.typed
time_measure_decorator.egg-info/PKG-INFO
time_measure_decorator.egg-info/SOURCES.txt
time_measure_decorator.egg-info/dependency_links.txt
time_measure_decorator.egg-info/top_level.txt